efopen/__init__.py
efopen/_version.py
efopen/demo_templateresolver.py
efopen/ef_app_config_reader.py
efopen/ef_aws_resolver.py
efopen/ef_cf.py
efopen/ef_cf_diff.py
efopen/ef_check_config.py
efopen/ef_conf_utils.py
efopen/ef_config.py
efopen/ef_config_resolver.py
efopen/ef_context.py
efopen/ef_generate.py
efopen/ef_instanceinit.py
efopen/ef_instanceinit_config_reader.py
efopen/ef_password.py
efopen/ef_resolve_config.py
efopen/ef_service_registry.py
efopen/ef_site_config.py
efopen/ef_template_resolver.py
efopen/ef_utils.py
efopen/ef_version.py
efopen/ef_version_resolver.py
efopen/newrelic_executor.py
efopen/newrelic_interface.py
ef_open-1.42.3.dist-info/LICENSE
ef_open-1.42.3.dist-info/METADATA
ef_open-1.42.3.dist-info/NOTICE
ef_open-1.42.3.dist-info/WHEEL
ef_open-1.42.3.dist-info/entry_points.txt
ef_open-1.42.3.dist-info/top_level.txt
ef_open-1.42.3.dist-info/RECORD
