Metadata-Version: 2.1
Name: ef-open
Version: 1.42.3
Summary: CloudFormation Tools by Ellation
Home-page: https://github.com/crunchyroll/ef-open
Author: Ellation, Inc.
Author-email: ops@ellation.com
License: Apache License 2.0
Platform: UNKNOWN
Requires-Dist: boto3 (>=1.17.112)
Requires-Dist: click (<=7.1.2)
Requires-Dist: PyYAML (<=5.4.1)
Requires-Dist: cfn-lint
Requires-Dist: netaddr (==0.8.0)
Requires-Dist: requests (<=2.25.1)
Requires-Dist: tenacity (==7.0.0)
Requires-Dist: yamllint (<=1.25.0)
Requires-Dist: python-dateutil (==2.8.2)
Provides-Extra: test
Requires-Dist: mock ; extra == 'test'
Requires-Dist: pylint ; extra == 'test'
